alarm_clk.v
`timescale 1ns / 1ps
module alarm_clk (
    clk, reset, shutdown, reset_minute, reset_hour, alarm_minute, alarm_hour,
    second, minute, hour, alarm_flag
);

// Inputs
input clk, reset, shutdown;               // system clock, reset, shutdown button
input [5:0] reset_minute;                 // Reset minute input (0-59)
input [4:0] reset_hour;                   // Reset hour input (0-23)
input [5:0] alarm_minute;                 // Alarm minute input (0-59)
input [4:0] alarm_hour;                   // Alarm hour input (0-23)

// Outputs
output [5:0] second, minute;              // Seconds and minutes output (0-59)
output [4:0] hour;                        // Hours output (0-23)
output reg alarm_flag;                    // Alarm flag (1 when alarm active)

// Internal Registers
reg [5:0] sec_counter;                    // Seconds counter
reg [5:0] min_counter;                    // Minutes counter
reg [4:0] hr_counter;                     // Hours counter
reg [5:0] prev_minute;                    // Store previous minute to detect changes
reg alarm_active;                         // Flag to track if alarm is currently active

// 1. Timekeeping
// This module increments the time (seconds, minutes, hours) based on the clock.
always @(posedge clk or posedge reset) begin
    if (reset) begin
        sec_counter <= 0;
        min_counter <= reset_minute;
        hr_counter <= reset_hour;
        alarm_flag <= 0;                  // Reset alarm flag on reset
        prev_minute <= reset_minute;      // Store initial minute
        alarm_active <= 0;                // Reset alarm active flag
    end else begin
        // Increment seconds
        if (sec_counter == 59) begin
            sec_counter <= 0;
            // Increment minutes when seconds overflow
            if (min_counter == 59) begin
                min_counter <= 0;
                // Increment hours when minutes overflow
                if (hr_counter == 23)
                    hr_counter <= 0;
                else
                    hr_counter <= hr_counter + 1;
            end else begin
                min_counter <= min_counter + 1;
            end
        end else begin
            sec_counter <= sec_counter + 1;
        end
    end
end

// 2. Alarm Logic
// This module handles alarm flag, setting it when the time matches the alarm.
always @(posedge clk or posedge reset) begin
    if (reset) begin
        alarm_flag <= 0;                  // Reset alarm flag on reset
        alarm_active <= 0;                // Reset active alarm flag
    end else begin
        // Shutdown Check
        // Only reset alarm if it's active and shutdown is triggered
        if (shutdown && alarm_active) begin
            alarm_flag <= 0;              // Deactivate the currently active alarm
            alarm_active <= 0;            // Mark alarm as inactive
        end else begin
            // Alarm Time Match
            if (hour == alarm_hour && minute == alarm_minute && !alarm_active) begin
                alarm_flag <= 1;          // Set alarm flag when the time matches
                alarm_active <= 1;        // Mark alarm as active
            end
            // Deactivate Alarm if Time Changes
            else if (hour != alarm_hour || minute != alarm_minute) begin
                alarm_flag <= 0;          // Reset alarm flag when time no longer matches
                alarm_active <= 0;        // Mark alarm as inactive
            end
        end
    end
end

// 3. Output Assignments
// This section assigns the current time to the outputs: second, minute, and hour.
assign second = sec_counter;
assign minute = min_counter;
assign hour = hr_counter;

endmodule

tb_alarm_clk.v
`timescale 1ns / 1ps
module tb_alarm_clk;

// Inputs
reg clk;
reg reset;
reg shutdown;
reg [5:0] reset_minute;
reg [4:0] reset_hour;
reg [5:0] alarm_minute;
reg [4:0] alarm_hour;

// Outputs
wire [5:0] second;
wire [5:0] minute;
wire [4:0] hour;
wire alarm_flag;

// Instantiate AlarmClock
alarm_clk uut (
    .clk(clk),
    .reset(reset),
    .shutdown(shutdown),
    .reset_minute(reset_minute),
    .reset_hour(reset_hour),
    .alarm_minute(alarm_minute),
    .alarm_hour(alarm_hour),
    .second(second),
    .minute(minute),
    .hour(hour),
    .alarm_flag(alarm_flag)
);

// Clock Generation
initial clk = 0;
always #5 clk = ~clk; // 100 MHz clock

// Simulation
initial begin
    // Enable waveform dumping for GTKWave
    $dumpfile("alarm_clk.vcd");
    $dumpvars(0, tb_alarm_clk);

    // Initialize inputs
    reset = 1;
    shutdown = 0;
    reset_hour = 1;
    reset_minute = 20;
    alarm_hour = 0;
    alarm_minute = 0;

    // Release reset
    #10;
    reset = 0;

    // Alarm 1 at 02:00
    alarm_hour = 2;
    alarm_minute = 0;
    wait (hour == 2 && minute == 0);
    $display("Time = %0d:%0d:%0d -> Alarm 1 ON: %b", hour, minute, second, alarm_flag);

    // Shutdown at 02:00:30
    wait(second == 30);
    shutdown = 1;
    #10;
    shutdown = 0;
    $display("Shutdown at Time = %0d:%0d:%0d -> Alarm 1 OFF: %b", hour, minute, second, alarm_flag);

    // Alarm 2 at 03:15
    alarm_hour = 3;
    alarm_minute = 15;
    wait(hour == 3 && minute == 15);
    $display("Time = %0d:%0d:%0d -> Alarm 2 ON: %b", hour, minute, second, alarm_flag);

    // Wait until 03:16 (alarm deactivates automatically)
    wait (minute == 16);
    $display("Time = %0d:%0d:%0d -> Alarm 2 OFF: %b", hour, minute, second, alarm_flag);

    #6000;
    $finish;
end

endmodule

alarm_clk.vcd
$date
	Thu Sep 24 20:52:38 2026
$end
$version
	Icarus Verilog
$end
$timescale
	1ps
$end
$scope module tb_alarm_clk $end
$var wire 6 ! second [5:0] $end
$var wire 6 " minute [5:0] $end
$var wire 5 # hour [4:0] $end
$var wire 1 $ alarm_flag $end
$var reg 5 % alarm_hour [4:0] $end
$var reg 6 & alarm_minute [5:0] $end
$var reg 1 ' clk $end
$var reg 1 ( reset $end
$var reg 5 ) reset_hour [4:0] $end
$var reg 6 * reset_minute [5:0] $end
$var reg 1 + shutdown $end
$scope module uut $end
$var wire 5 , alarm_hour [4:0] $end
$var wire 6 - alarm_minute [5:0] $end
$var wire 1 ' clk $end
$var wire 5 . hour [4:0] $end
$var wire 6 / minute [5:0] $end
$var wire 1 ( reset $end
$var wire 5 0 reset_hour [4:0] $end
$var wire 6 1 reset_minute [5:0] $end
$var wire 6 2 second [5:0] $end
$var wire 1 + shutdown $end
$var reg 1 3 alarm_active $end
$var reg 1 $ alarm_flag $end
$var reg 5 4 hr_counter [4:0] $end
$var reg 6 5 min_counter [5:0] $end
$var reg 6 6 prev_minute [5:0] $end
$var reg 6 7 sec_counter [5:0] $end
$upscope $end
$upscope $end
$enddefinitions $end
$comment Show the parameter values. $end
$dumpall
$end
#0
$dumpvars
b0 7
b10100 6
b10100 5
b1 4
03
b0 2
b10100 1
b1 0
b10100 /
b1 .
b0 -
b0 ,
0+
b10100 *
b1 )
1(
0'
b0 &
b0 %
0$
b1 #
b10100 "
b0 !
$end
#5000
1'
#10000
0'
b10 %
b10 ,
0(
#15000
b1 !
b1 2
b1 7
1'
#20000
0'
#25000
b10 !
b10 2
b10 7
1'
#30000
0'
#35000
b11 !
b11 2
b11 7
1'
#40000
0'
#45000
b100 !
b100 2
b100 7
1'
#50000
0'
#55000
b101 !
b101 2
b101 7
1'
#60000
0'
#65000
b110 !
b110 2
b110 7
1'
#70000
0'
#75000
b111 !
b111 2
b111 7
1'
#80000
0'
#85000
b1000 !
b1000 2
b1000 7
1'
#90000
0'
#95000
b1001 !
b1001 2
b1001 7
1'
#100000
0'
#105000
b1010 !
b1010 2
b1010 7
1'
#110000
0'
#115000
b1011 !
b1011 2
b1011 7
1'
#120000
0'
#125000
b1100 !
b1100 2
b1100 7
1'
#130000
0'
#135000
b1101 !
b1101 2
b1101 7
1'
#140000
0'
#145000
b1110 !
b1110 2
b1110 7
1'
#150000
0'
#155000
b1111 !
b1111 2
b1111 7
1'
#160000
0'
#165000
b10000 !
b10000 2
b10000 7
1'
#170000
0'
#175000
b10001 !
b10001 2
b10001 7
1'
#180000
0'
#185000
b10010 !
b10010 2
b10010 7
1'
#190000
0'
#195000
b10011 !
b10011 2
b10011 7
1'
#200000
0'
#205000
b10100 !
b10100 2
b10100 7
1'
#210000
0'
#215000
b10101 !
b10101 2
b10101 7
1'
#220000
0'
#225000
b10110 !
b10110 2
b10110 7
1'
#230000
0'
#235000
b10111 !
b10111 2
b10111 7
1'
#240000
0'
#245000
b11000 !
b11000 2
b11000 7
1'
#250000
0'
#255000
b11001 !
b11001 2
b11001 7
1'
#260000
0'
#265000
b11010 !
b11010 2
b11010 7
1'
#270000
0'
#275000
b11011 !
b11011 2
b11011 7
1'
#280000
0'
#285000
b11100 !
b11100 2
b11100 7
1'
#290000
0'
#295000
b11101 !
b11101 2
b11101 7
1'
#300000
0'
#305000
b11110 !
b11110 2
b11110 7
1'
#310000
0'
#315000
b11111 !
b11111 2
b11111 7
1'
#320000
0'
#325000
b100000 !
b100000 2
b100000 7
1'
#330000
0'
#335000
b100001 !
b100001 2
b100001 7
1'
#340000
0'
#345000
b100010 !
b100010 2
b100010 7
1'
#350000
0'
#355000
b100011 !
b100011 2
b100011 7
1'
#360000
0'
#365000
b100100 !
b100100 2
b100100 7
1'
#370000
0'
#375000
b100101 !
b100101 2
b100101 7
1'
#380000
0'
#385000
b100110 !
b100110 2
b100110 7
1'
#390000
0'
#395000
b100111 !
b100111 2
b100111 7
1'
#400000
0'
#405000
b101000 !
b101000 2
b101000 7
1'
#410000
0'
#415000
b101001 !
b101001 2
b101001 7
1'
#420000
0'
#425000
b101010 !
b101010 2
b101010 7
1'
#430000
0'
#435000
b101011 !
b101011 2
b101011 7
1'
#440000
0'
#445000
b101100 !
b101100 2
b101100 7
1'
#450000
0'
#455000
b101101 !
b101101 2
b101101 7
1'
#460000
0'
#465000
b101110 !
b101110 2
b101110 7
1'
#470000
0'
#475000
b101111 !
b101111 2
b101111 7
1'
#480000
0'
#485000
b110000 !
b110000 2
b110000 7
1'
#490000
0'
#495000
b110001 !
b110001 2
b110001 7
1'
#500000
0'
#505000
b110010 !
b110010 2
b110010 7
1'
#510000
0'
#515000
b110011 !
b110011 2
b110011 7
1'
#520000
0'
#525000
b110100 !
b110100 2
b110100 7
1'
#530000
0'
#535000
b110101 !
b110101 2
b110101 7
1'
#540000
0'
#545000
b110110 !
b110110 2
b110110 7
1'
#550000
0'
#555000
b110111 !
b110111 2
b110111 7
1'
#560000
0'
#565000
b111000 !
b111000 2
b111000 7
1'
#570000
0'
#575000
b111001 !
b111001 2
b111001 7
1'
#580000
0'
#585000
b111010 !
b111010 2
b111010 7
1'
#590000
0'
#595000
b111011 !
b111011 2
b111011 7
1'
#600000
0'
#605000
b10101 "
b10101 /
b10101 5
b0 !
b0 2
b0 7
1'
#610000
0'
#615000
b1 !
b1 2
b1 7
1'
#620000
0'
#625000
b10 !
b10 2
b10 7
1'
#630000
0'
#635000
b11 !
b11 2
b11 7
1'
#640000
0'
#645000
b100 !
b100 2
b100 7
1'
#650000
0'
#655000
b101 !
b101 2
b101 7
1'
#660000
0'
#665000
b110 !
b110 2
b110 7
1'
#670000
0'
#675000
b111 !
b111 2
b111 7
1'
#680000
0'
#685000
b1000 !
b1000 2
b1000 7
1'
#690000
0'
#695000
b1001 !
b1001 2
b1001 7
1'
#700000
0'
#705000
b1010 !
b1010 2
b1010 7
1'
#710000
0'
#715000
b1011 !
b1011 2
b1011 7
1'
#720000
0'
#725000
b1100 !
b1100 2
b1100 7
1'
#730000
0'
#735000
b1101 !
b1101 2
b1101 7
1'
#740000
0'
#745000
b1110 !
b1110 2
b1110 7
1'
#750000
0'
#755000
b1111 !
b1111 2
b1111 7
1'
#760000
0'
#765000
b10000 !
b10000 2
b10000 7
1'
#770000
0'
#775000
b10001 !
b10001 2
b10001 7
1'
#780000
0'
#785000
b10010 !
b10010 2
b10010 7
1'
#790000
0'
#795000
b10011 !
b10011 2
b10011 7
1'
#800000
0'
#805000
b10100 !
b10100 2
b10100 7
1'
#810000
0'
#815000
b10101 !
b10101 2
b10101 7
1'
#820000
0'
#825000
b10110 !
b10110 2
b10110 7
1'
#830000
0'
#835000
b10111 !
b10111 2
b10111 7
1'
#840000
0'
#845000
b11000 !
b11000 2
b11000 7
1'
#850000
0'
#855000
b11001 !
b11001 2
b11001 7
1'
#860000
0'
#865000
b11010 !
b11010 2
b11010 7
1'
#870000
0'
#875000
b11011 !
b11011 2
b11011 7
1'
#880000
0'
#885000
b11100 !
b11100 2
b11100 7
1'
#890000
0'
#895000
b11101 !
b11101 2
b11101 7
1'
#900000
0'
#905000
b11110 !
b11110 2
b11110 7
1'
#910000
0'
#915000
b11111 !
b11111 2
b11111 7
1'
#920000
0'
#925000
b100000 !
b100000 2
b100000 7
1'
#930000
0'
#935000
b100001 !
b100001 2
b100001 7
1'
#940000
0'
#945000
b100010 !
b100010 2
b100010 7
1'
#950000
0'
#955000
b100011 !
b100011 2
b100011 7
1'
#960000
0'
#965000
b100100 !
b100100 2
b100100 7
1'
#970000
0'
#975000
b100101 !
b100101 2
b100101 7
1'
#980000
0'
#985000
b100110 !
b100110 2
b100110 7
1'
#990000
0'
#995000
b100111 !
b100111 2
b100111 7
1'
#1000000
0'
#1005000
b101000 !
b101000 2
b101000 7
1'
#1010000
0'
#1015000
b101001 !
b101001 2
b101001 7
1'
#1020000
0'
#1025000
b101010 !
b101010 2
b101010 7
1'
#1030000
0'
#1035000
b101011 !
b101011 2
b101011 7
1'
#1040000
0'
#1045000
b101100 !
b101100 2
b101100 7
1'
#1050000
0'
#1055000
b101101 !
b101101 2
b101101 7
1'
#1060000
0'
#1065000
b101110 !
b101110 2
b101110 7
1'
#1070000
0'
#1075000
b101111 !
b101111 2
b101111 7
1'
#1080000
0'
#1085000
b110000 !
b110000 2
b110000 7
1'
#1090000
0'
#1095000
b110001 !
b110001 2
b110001 7
1'
#1100000
0'
#1105000
b110010 !
b110010 2
b110010 7
1'
#1110000
0'
#1115000
b110011 !
b110011 2
b110011 7
1'
#1120000
0'
#1125000
b110100 !
b110100 2
b110100 7
1'
#1130000
0'
#1135000
b110101 !
b110101 2
b110101 7
1'
#1140000
0'
#1145000
b110110 !
b110110 2
b110110 7
1'
#1150000
0'
#1155000
b110111 !
b110111 2
b110111 7
1'
#1160000
0'
#1165000
b111000 !
b111000 2
b111000 7
1'
#1170000
0'
#1175000
b111001 !
b111001 2
b111001 7
1'
#1180000
0'
#1185000
b111010 !
b111010 2
b111010 7
1'
#1190000
0'
#1195000
b111011 !
b111011 2
b111011 7
1'
#1200000
0'
#1205000
b10110 "
b10110 /
b10110 5
b0 !
b0 2
b0 7
1'
#1210000
0'
#1215000
b1 !
b1 2
b1 7
1'
#1220000
0'
#1225000
b10 !
b10 2
b10 7
1'
#1230000
0'
#1235000
b11 !
b11 2
b11 7
1'
#1240000
0'
#1245000
b100 !
b100 2
b100 7
1'
#1250000
0'
#1255000
b101 !
b101 2
b101 7
1'
#1260000
0'
#1265000
b110 !
b110 2
b110 7
1'
#1270000
0'
#1275000
b111 !
b111 2
b111 7
1'
#1280000
0'
#1285000
b1000 !
b1000 2
b1000 7
1'
#1290000
0'
#1295000
b1001 !
b1001 2
b1001 7
1'
#1300000
0'
#1305000
b1010 !
b1010 2
b1010 7
1'
#1310000
0'
#1315000
b1011 !
b1011 2
b1011 7
1'
#1320000
0'
#1325000
b1100 !
b1100 2
b1100 7
1'
#1330000
0'
#1335000
b1101 !
b1101 2
b1101 7
1'
#1340000
0'
#1345000
b1110 !
b1110 2
b1110 7
1'
#1350000
0'
#1355000
b1111 !
b1111 2
b1111 7
1'
#1360000
0'
#1365000
b10000 !
b10000 2
b10000 7
1'
#1370000
0'
#1375000
b10001 !
b10001 2
b10001 7
1'
#1380000
0'
#1385000
b10010 !
b10010 2
b10010 7
1'
#1390000
0'
#1395000
b10011 !
b10011 2
b10011 7
1'
#1400000
0'
#1405000
b10100 !
b10100 2
b10100 7
1'
#1410000
0'
#1415000
b10101 !
b10101 2
b10101 7
1'
#1420000
0'
#1425000
b10110 !
b10110 2
b10110 7
1'
#1430000
0'
#1435000
b10111 !
b10111 2
b10111 7
1'
#1440000
0'
#1445000
b11000 !
b11000 2
b11000 7
1'
#1450000
0'
#1455000
b11001 !
b11001 2
b11001 7
1'
#1460000
0'
#1465000
b11010 !
b11010 2
b11010 7
1'
#1470000
0'
#1475000
b11011 !
b11011 2
b11011 7
1'
#1480000
0'
#1485000
b11100 !
b11100 2
b11100 7
1'
#1490000
0'
#1495000
b11101 !
b11101 2
b11101 7
1'
#1500000
0'
#1505000
b11110 !
b11110 2
b11110 7
1'
#1510000
0'
#1515000
b11111 !
b11111 2
b11111 7
1'
#1520000
0'
#1525000
b100000 !
b100000 2
b100000 7
1'
#1530000
0'
#1535000
b100001 !
b100001 2
b100001 7
1'
#1540000
0'
#1545000
b100010 !
b100010 2
b100010 7
1'
#1550000
0'
#1555000
b100011 !
b100011 2
b100011 7
1'
#1560000
0'
#1565000
b100100 !
b100100 2
b100100 7
1'
#1570000
0'
#1575000
b100101 !
b100101 2
b100101 7
1'
#1580000
0'
#1585000
b100110 !
b100110 2
b100110 7
1'
#1590000
0'
#1595000
b100111 !
b100111 2
b100111 7
1'
#1600000
0'
#1605000
b101000 !
b101000 2
b101000 7
1'
#1610000
0'
#1615000
b101001 !
b101001 2
b101001 7
1'
#1620000
0'
#1625000
b101010 !
b101010 2
b101010 7
1'
#1630000
0'
#1635000
b101011 !
b101011 2
b101011 7
1'
#1640000
0'
#1645000
b101100 !
b101100 2
b101100 7
1'
#1650000
0'
#1655000
b101101 !
b101101 2
b101101 7
1'
#1660000
0'
#1665000
b101110 !
b101110 2
b101110 7
1'
#1670000
0'
#1675000
b101111 !
b101111 2
b101111 7
1'
#1680000
0'
#1685000
b110000 !
b110000 2
b110000 7
1'
#1690000
0'
#1695000
b110001 !
b110001 2
b110001 7
1'
#1700000
0'
#1705000
b110010 !
b110010 2
b110010 7
1'
#1710000
0'
#1715000
b110011 !
b110011 2
b110011 7
1'
#1720000
0'
#1725000
b110100 !
b110100 2
b110100 7
1'
#1730000
0'
#1735000
b110101 !
b110101 2
b110101 7
1'
#1740000
0'
#1745000
b110110 !
b110110 2
b110110 7
1'
#1750000
0'
#1755000
b110111 !
b110111 2
b110111 7
1'
#1760000
0'
#1765000
b111000 !
b111000 2
b111000 7
1'
#1770000
0'
#1775000
b111001 !
b111001 2
b111001 7
1'
#1780000
0'
#1785000
b111010 !
b111010 2
b111010 7
1'
#1790000
0'
#1795000
b111011 !
b111011 2
b111011 7
1'
#1800000
0'
#1805000
b10111 "
b10111 /
b10111 5
b0 !
b0 2
b0 7
1'
#1810000
0'
#1815000
b1 !
b1 2
b1 7
1'
#1820000
0'
#1825000
b10 !
b10 2
b10 7
1'
#1830000
0'
#1835000
b11 !
b11 2
b11 7
1'
#1840000
0'
#1845000
b100 !
b100 2
b100 7
1'
#1850000
0'
#1855000
b101 !
b101 2
b101 7
1'
#1860000
0'
#1865000
b110 !
b110 2
b110 7
1'
#1870000
0'
#1875000
b111 !
b111 2
b111 7
1'
#1880000
0'
#1885000
b1000 !
b1000 2
b1000 7
1'
#1890000
0'
#1895000
b1001 !
b1001 2
b1001 7
1'
#1900000
0'
#1905000
b1010 !
b1010 2
b1010 7
1'
#1910000
0'
#1915000
b1011 !
b1011 2
b1011 7
1'
#1920000
0'
#1925000
b1100 !
b1100 2
b1100 7
1'
#1930000
0'
#1935000
b1101 !
b1101 2
b1101 7
1'
#1940000
0'
#1945000
b1110 !
b1110 2
b1110 7
1'
#1950000
0'
#1955000
b1111 !
b1111 2
b1111 7
1'
#1960000
0'
#1965000
b10000 !
b10000 2
b10000 7
1'
#1970000
0'
#1975000
b10001 !
b10001 2
b10001 7
1'
#1980000
0'
#1985000
b10010 !
b10010 2
b10010 7
1'
#1990000
0'
#1995000
b10011 !
b10011 2
b10011 7
1'
#2000000
0'
#2005000
b10100 !
b10100 2
b10100 7
1'
#2010000
0'
#2015000
b10101 !
b10101 2
b10101 7
1'
#2020000
0'
#2025000
b10110 !
b10110 2
b10110 7
1'
#2030000
0'
#2035000
b10111 !
b10111 2
b10111 7
1'
#2040000
0'
#2045000
b11000 !
b11000 2
b11000 7
1'
#2050000
0'
#2055000
b11001 !
b11001 2
b11001 7
1'
#2060000
0'
#2065000
b11010 !
b11010 2
b11010 7
1'
#2070000
0'
#2075000
b11011 !
b11011 2
b11011 7
1'
#2080000
0'
#2085000
b11100 !
b11100 2
b11100 7
1'
#2090000
0'
#2095000
b11101 !
b11101 2
b11101 7
1'
#2100000
0'
#2105000
b11110 !
b11110 2
b11110 7
1'
#2110000
0'
#2115000
b11111 !
b11111 2
b11111 7
1'
#2120000
0'
#2125000
b100000 !
b100000 2
b100000 7
1'
#2130000
0'
#2135000
b100001 !
b100001 2
b100001 7
1'
#2140000
0'
#2145000
b100010 !
b100010 2
b100010 7
1'
#2150000
0'
#2155000
b100011 !
b100011 2
b100011 7
1'
#2160000
0'
#2165000
b100100 !
b100100 2
b100100 7
1'
#2170000
0'
#2175000
b100101 !
b100101 2
b100101 7
1'
#2180000
0'
#2185000
b100110 !
b100110 2
b100110 7
1'
#2190000
0'
#2195000
b100111 !
b100111 2
b100111 7
1'
#2200000
0'
#2205000
b101000 !
b101000 2
b101000 7
1'
#2210000
0'
#2215000
b101001 !
b101001 2
b101001 7
1'
#2220000
0'
#2225000
b101010 !
b101010 2
b101010 7
1'
#2230000
0'
#2235000
b101011 !
b101011 2
b101011 7
1'
#2240000
0'
#2245000
b101100 !
b101100 2
b101100 7
1'
#2250000
0'
#2255000
b101101 !
b101101 2
b101101 7
1'
#2260000
0'
#2265000
b101110 !
b101110 2
b101110 7
1'
#2270000
0'
#2275000
b101111 !
b101111 2
b101111 7
1'
#2280000
0'
#2285000
b110000 !
b110000 2
b110000 7
1'
#2290000
0'
#2295000
b110001 !
b110001 2
b110001 7
1'
#2300000
0'
#2305000
b110010 !
b110010 2
b110010 7
1'
#2310000
0'
#2315000
b110011 !
b110011 2
b110011 7
1'
#2320000
0'
#2325000
b110100 !
b110100 2
b110100 7
1'
#2330000
0'
#2335000
b110101 !
b110101 2
b110101 7
1'
#2340000
0'
#2345000
b110110 !
b110110 2
b110110 7
1'
#2350000
0'
#2355000
b110111 !
b110111 2
b110111 7
1'
#2360000
0'
#2365000
b111000 !
b111000 2
b111000 7
1'
#2370000
0'
#2375000
b111001 !
b111001 2
b111001 7
1'
#2380000
0'
#2385000
b111010 !
b111010 2
b111010 7
1'
#2390000
0'
#2395000
b111011 !
b111011 2
b111011 7
1'
#2400000
0'
#2405000
b11000 "
b11000 /
b11000 5
b0 !
b0 2
b0 7
1'
#2410000
0'
#2415000
b1 !
b1 2
b1 7
1'
#2420000
0'
#2425000
b10 !
b10 2
b10 7
1'
#2430000
0'
#2435000
b11 !
b11 2
b11 7
1'
#2440000
0'
#2445000
b100 !
b100 2
b100 7
1'
#2450000
0'
#2455000
b101 !
b101 2
b101 7
1'
#2460000
0'
#2465000
b110 !
b110 2
b110 7
1'
#2470000
0'
#2475000
b111 !
b111 2
b111 7
1'
#2480000
0'
#2485000
b1000 !
b1000 2
b1000 7
1'
#2490000
0'
#2495000
b1001 !
b1001 2
b1001 7
1'
#2500000
0'
#2505000
b1010 !
b1010 2
b1010 7
1'
#2510000
0'
#2515000
b1011 !
b1011 2
b1011 7
1'
#2520000
0'
#2525000
b1100 !
b1100 2
b1100 7
1'
#2530000
0'
#2535000
b1101 !
b1101 2
b1101 7
1'
#2540000
0'
#2545000
b1110 !
b1110 2
b1110 7
1'
#2550000
0'
#2555000
b1111 !
b1111 2
b1111 7
1'
#2560000
0'
#2565000
b10000 !
b10000 2
b10000 7
1'
#2570000
0'
#2575000
b10001 !
b10001 2
b10001 7
1'
#2580000
0'
#2585000
b10010 !
b10010 2
b10010 7
1'
#2590000
0'
#2595000
b10011 !
b10011 2
b10011 7
1'
#2600000
0'
#2605000
b10100 !
b10100 2
b10100 7
1'
#2610000
0'
#2615000
b10101 !
b10101 2
b10101 7
1'
#2620000
0'
#2625000
b10110 !
b10110 2
b10110 7
1'
#2630000
0'
#2635000
b10111 !
b10111 2
b10111 7
1'
#2640000
0'
#2645000
b11000 !
b11000 2
b11000 7
1'
#2650000
0'
#2655000
b11001 !
b11001 2
b11001 7
1'
#2660000
0'
#2665000
b11010 !
b11010 2
b11010 7
1'
#2670000
0'
#2675000
b11011 !
b11011 2
b11011 7
1'
#2680000
0'
#2685000
b11100 !
b11100 2
b11100 7
1'
#2690000
0'
#2695000
b11101 !
b11101 2
b11101 7
1'
#2700000
0'
#2705000
b11110 !
b11110 2
b11110 7
1'
#2710000
0'
#2715000
b11111 !
b11111 2
b11111 7
1'
#2720000
0'
#2725000
b100000 !
b100000 2
b100000 7
1'
#2730000
0'
#2735000
b100001 !
b100001 2
b100001 7
1'
#2740000
0'
#2745000
b100010 !
b100010 2
b100010 7
1'
#2750000
0'
#2755000
b100011 !
b100011 2
b100011 7
1'
#2760000
0'
#2765000
b100100 !
b100100 2
b100100 7
1'
#2770000
0'
#2775000
b100101 !
b100101 2
b100101 7
1'
#2780000
0'
#2785000
b100110 !
b100110 2
b100110 7
1'
#2790000
0'
#2795000
b100111 !
b100111 2
b100111 7
1'
#2800000
0'
#2805000
b101000 !
b101000 2
b101000 7
1'
#2810000
0'
#2815000
b101001 !
b101001 2
b101001 7
1'
#2820000
0'
#2825000
b101010 !
b101010 2
b101010 7
1'
#2830000
0'
#2835000
b101011 !
b101011 2
b101011 7
1'
#2840000
0'
#2845000
b101100 !
b101100 2
b101100 7
1'
#2850000
0'
#2855000
b101101 !
b101101 2
b101101 7
1'
#2860000
0'
#2865000
b101110 !
b101110 2
b101110 7
1'
#2870000
0'
#2875000
b101111 !
b101111 2
b101111 7
1'
#2880000
0'
#2885000
b110000 !
b110000 2
b110000 7
1'
#2890000
0'
#2895000
b110001 !
b110001 2
b110001 7
1'
#2900000
0'
#2905000
b110010 !
b110010 2
b110010 7
1'
#2910000
0'
#2915000
b110011 !
b110011 2
b110011 7
1'
#2920000
0'
#2925000
b110100 !
b110100 2
b110100 7
1'
#2930000
0'
#2935000
b110101 !
b110101 2
b110101 7
1'
#2940000
0'
#2945000
b110110 !
b110110 2
b110110 7
1'
#2950000
0'
#2955000
b110111 !
b110111 2
b110111 7
1'
#2960000
0'
#2965000
b111000 !
b111000 2
b111000 7
1'
#2970000
0'
#2975000
b111001 !
b111001 2
b111001 7
1'
#2980000
0'
#2985000
b111010 !
b111010 2
b111010 7
1'
#2990000
0'
#2995000
b111011 !
b111011 2
b111011 7
1'
#3000000
0'
#3005000
b11001 "
b11001 /
b11001 5
b0 !
b0 2
b0 7
1'
#3010000
0'
#3015000
b1 !
b1 2
b1 7
1'
#3020000
0'
#3025000
b10 !
b10 2
b10 7
1'
#3030000
0'
#3035000
b11 !
b11 2
b11 7
1'
#3040000
0'
#3045000
b100 !
b100 2
b100 7
1'
#3050000
0'
#3055000
b101 !
b101 2
b101 7
1'
#3060000
0'
#3065000
b110 !
b110 2
b110 7
1'
#3070000
0'
#3075000
b111 !
b111 2
b111 7
1'
#3080000
0'
#3085000
b1000 !
b1000 2
b1000 7
1'
#3090000
0'
#3095000
b1001 !
b1001 2
b1001 7
1'
#3100000
0'
#3105000
b1010 !
b1010 2
b1010 7
1'
#3110000
0'
#3115000
b1011 !
b1011 2
b1011 7
1'
#3120000
0'
#3125000
b1100 !
b1100 2
b1100 7
1'
#3130000
0'
#3135000
b1101 !
b1101 2
b1101 7
1'
#3140000
0'
#3145000
b1110 !
b1110 2
b1110 7
1'
#3150000
0'
#3155000
b1111 !
b1111 2
b1111 7
1'
#3160000
0'
#3165000
b10000 !
b10000 2
b10000 7
1'
#3170000
0'
#3175000
b10001 !
b10001 2
b10001 7
1'
#3180000
0'
#3185000
b10010 !
b10010 2
b10010 7
1'
#3190000
0'
#3195000
b10011 !
b10011 2
b10011 7
1'
#3200000
0'
#3205000
b10100 !
b10100 2
b10100 7
1'
#3210000
0'
#3215000
b10101 !
b10101 2
b10101 7
1'
#3220000
0'
#3225000
b10110 !
b10110 2
b10110 7
1'
#3230000
0'
#3235000
b10111 !
b10111 2
b10111 7
1'
#3240000
0'
#3245000
b11000 !
b11000 2
b11000 7
1'
#3250000
0'
#3255000
b11001 !
b11001 2
b11001 7
1'
#3260000
0'
#3265000
b11010 !
b11010 2
b11010 7
1'
#3270000
0'
#3275000
b11011 !
b11011 2
b11011 7
1'
#3280000
0'
#3285000
b11100 !
b11100 2
b11100 7
1'
#3290000
0'
#3295000
b11101 !
b11101 2
b11101 7
1'
#3300000
0'
#3305000
b11110 !
b11110 2
b11110 7
1'
#3310000
0'
#3315000
b11111 !
b11111 2
b11111 7
1'
#3320000
0'
#3325000
b100000 !
b100000 2
b100000 7
1'
#3330000
0'
#3335000
b100001 !
b100001 2
b100001 7
1'
#3340000
0'
#3345000
b100010 !
b100010 2
b100010 7
1'
#3350000
0'
#3355000
b100011 !
b100011 2
b100011 7
1'
#3360000
0'
#3365000
b100100 !
b100100 2
b100100 7
1'
#3370000
0'
#3375000
b100101 !
b100101 2
b100101 7
1'
#3380000
0'
#3385000
b100110 !
b100110 2
b100110 7
1'
#3390000
0'
#3395000
b100111 !
b100111 2
b100111 7
1'
#3400000
0'
#3405000
b101000 !
b101000 2
b101000 7
1'
#3410000
0'
#3415000
b101001 !
b101001 2
b101001 7
1'
#3420000
0'
#3425000
b101010 !
b101010 2
b101010 7
1'
#3430000
0'
#3435000
b101011 !
b101011 2
b101011 7
1'
#3440000
0'
#3445000
b101100 !
b101100 2
b101100 7
1'
#3450000
0'
#3455000
b101101 !
b101101 2
b101101 7
1'
#3460000
0'
#3465000
b101110 !
b101110 2
b101110 7
1'
#3470000
0'
#3475000
b101111 !
b101111 2
b101111 7
1'
#3480000
0'
#3485000
b110000 !
b110000 2
b110000 7
1'
#3490000
0'
#3495000
b110001 !
b110001 2
b110001 7
1'
#3500000
0'
#3505000
b110010 !
b110010 2
b110010 7
1'
#3510000
0'
#3515000
b110011 !
b110011 2
b110011 7
1'
#3520000
0'
#3525000
b110100 !
b110100 2
b110100 7
1'
#3530000
0'
#3535000
b110101 !
b110101 2
b110101 7
1'
#3540000
0'
#3545000
b110110 !
b110110 2
b110110 7
1'
#3550000
0'
#3555000
b110111 !
b110111 2
b110111 7
1'
#3560000
0'
#3565000
b111000 !
b111000 2
b111000 7
1'
#3570000
0'
#3575000
b111001 !
b111001 2
b111001 7
1'
#3580000
0'
